flash_colreduce/__init__.py
flash_colreduce/flash.py
flash_colreduce/naive.py
flash_colreduce-0.2.1.dist-info/licenses/LICENSE
flash_colreduce-0.2.1.dist-info/METADATA
flash_colreduce-0.2.1.dist-info/WHEEL
flash_colreduce-0.2.1.dist-info/top_level.txt
flash_colreduce-0.2.1.dist-info/RECORD
