Metadata-Version: 2.4
Name: flash-colreduce
Version: 0.2.1
Summary: Fast, memory-efficient attention column reduction (e.g., sum, mean, max)
Author: Z Lab
License: MIT License
Project-URL: Homepage, https://github.com/z-lab/flash-colreduce
Project-URL: Issues, https://github.com/z-lab/flash-colreduce/issues
Keywords: triton,pytorch,cuda,attention,transformers,gpu,kernels
Classifier: License :: OSI Approved :: MIT License
Classifier: Programming Language :: Python :: 3
Classifier: Programming Language :: Python :: 3 :: Only
Classifier: Programming Language :: Python :: 3.10
Classifier: Programming Language :: Python :: 3.11
Classifier: Programming Language :: Python :: 3.12
Classifier: Topic :: Scientific/Engineering :: Artificial Intelligence
Classifier: Topic :: Scientific/Engineering :: Mathematics
Requires-Python: >=3.10
License-File: LICENSE
Requires-Dist: torch>=2.1
Requires-Dist: triton>=3.0.0
Provides-Extra: test
Requires-Dist: pytest>=7; extra == "test"
Requires-Dist: pytest-cov>=4; extra == "test"
Provides-Extra: dev
Requires-Dist: black>=24.0; extra == "dev"
Provides-Extra: bench
Requires-Dist: rich>=13.7; extra == "bench"
Requires-Dist: tqdm>=4.67; extra == "bench"
Provides-Extra: all
Requires-Dist: flash-colreduce[test]; extra == "all"
Requires-Dist: flash-colreduce[dev]; extra == "all"
Requires-Dist: flash-colreduce[bench]; extra == "all"
Dynamic: license-file
